<?xml version="1.0" encoding="utf-8" ?>
<gazette xmlns="http://hoerstemeier.com/tambon/" xmlns:geo="http://www.w3.org/2003/01/geo/wgs84_pos#">
  <!-- Main Election -->
  <entry description="Announcement of election date" title="ประกาศคณะกรรมการการเลือกตั้ง เรื่อง การสมัครรับเลือกตั้งสมาชิกสภาผู้แทนราษฎร" volume="128" page="155-156" issue="37 ก" uri="2554/A/037/155.PDF" publication="2011-05-14" sign="2011-05-14" signedby="อภิชาติ สุขัคคานนท์" signedbyfunction="ElectionCommissionPresident" />

  <!-- By-elections -->
  <entry description="Call for by-election in Nong Khai Constituency 3" title="คำสั่งคณะกรรมการการเลือกตั้ง ที่ ๒๒๑/๒๕๕๔ เรื่อง สั่งให้มีการเลือกตั้งสมาชิกสภาผู้แทนราษฎรจังหวัดสุโขทัย เขตเลือกตั้งที่ ๓ ใหม่" volume="128" page="22" issue="59 ก" uri="2554/A/059/22.PDF" publication="2011-07-27" sign="2011-07-21" signedby="อภิชาติ สุขัคคานนท์" signedbyfunction="ElectionCommissionPresident" />
  <entry description="Call for by-election in Sukhothai Constituency 2" title="คำสั่งคณะกรรมการการเลือกตั้ง ที่ ๒๒๐/๒๕๕๔ เรื่อง สั่งให้มีการเลือกตั้งสมาชิกสภาผู้แทนราษฎรจังหวัดหนองคาย เขตเลือกตั้งที่ ๒ ใหม่" volume="128" page="21" issue="59 ก" uri="2554/A/059/21.PDF" publication="2011-07-27" sign="2011-07-21" signedby="อภิชาติ สุขัคคานนท์" signedbyfunction="ElectionCommissionPresident" />
  <entry description="Call for by-election in Pathum Thani constituency 5" title="พระราชกฤษฎีกาให้มีการเลือกตั้งสมาชิกสภาผู้แทนราษฎรจังหวัดปทุมธานี เขตเลือกตั้งที่ ๕ แทนตำแหน่งที่ว่าง พ.ศ. ๒๕๕๕" volume="129" page="1-2" issue="29 ก" uri="2555/A/029/1.PDF" publication="2012-03-23" countersignedby="ยิ่งลักษณ์ ชินวัตร" countersignedbyfunction="PrimeMinister" sign="2012-03-23" />
  <entry description="Call for by-election in Chiang Mai constituency 3" title="พระราชกฤษฎีกาให้มีการเลือกตั้งสมาชิกสภาผู้แทนราษฎรจังหวัดเชียงใหม่ เขตเลือกตั้งที่ ๓ แทนตำแหน่งที่ว่าง พ.ศ. ๒๕๕๕" volume="129" page="1-2" issue="39 ก" uri="2555/A/039/1.PDF" publication="2012-05-04" countersignedby="ยิ่งลักษณ์ ชินวัตร" countersignedbyfunction="PrimeMinister" sign="2012-04-05" />
  <entry description="Call for by-election in Lamphun constituency 2" title="พระราชกฤษฎีกาให้มีการเลือกตั้งสมาชิกสภาผู้แทนราษฎรจังหวัดลำพูน เขตเลือกตั้งที่ ๒ แทนตำแหน่งที่ว่าง พ.ศ. ๒๕๕๕" volume="129" page="22-24" issue="71 ก" uri="2555/A/071/22.PDF" publication="2012-07-29" countersignedby="ยิ่งลักษณ์ ชินวัตร" countersignedbyfunction="PrimeMinister" sign="2012-07-29" />
  <entry description="Call for by-election in Chonburi constituency 2" title="พระราชกฤษฎีกา ให้มีการเลือกตั้งสมาชิกสภาผู้แทนราษฎรจังหวัดชลบุรี เขตเลือกตั้งที่ ๒ แทนตำแหน่งที่ว่าง พ.ศ. ๒๕๕๕" volume="129" page="1-2" issue="115 ก" uri="2555/A/115/1.PDF" publication="2012-12-09" countersignedby="ยิ่งลักษณ์ ชินวัตร" countersignedbyfunction="PrimeMinister" sign="2012-12-08" />
  <entry description="Call for by-election in Lopburi constituency 4" title="พระราชกฤษฎีกาให้มีการเลือกตั้งสมาชิกสภาผู้แทนราษฎร จังหวัดลพบุรี เขตเลือกตั้งที่ ๔ แทนตำแหน่งที่ว่าง พ.ศ. ๒๕๕๖" volume="130" page="1-3" issue="5 ก" uri="2556/A/005/1.PDF" publication="2013-01-17" countersignedby="ยิ่งลักษณ์ ชินวัตร" countersignedbyfunction="PrimeMinister" sign="2013-01-17" />
  <entry description="Call for by-election in Chiang Mai constituency 3" title="พระราชกฤษฎีกาให้มีการเลือกตั้งสมาชิกสภาผู้แทนราษฎรจังหวัดเชียงใหม่ เขตเลือกตั้งที่ ๓ แทนตำแหน่งที่ว่าง พ.ศ. ๒๕๕๖" volume="130" page="34-35" issue="30 ก" uri="2556/A/030/34.PDF" publication="2013-03-29" countersignedby="ยิ่งลักษณ์ ชินวัตร" countersignedbyfunction="PrimeMinister" sign="2013-03-28" />
  <entry description="Call for by-election in Chiang Mai constituency 12" title="พระราชกฤษฎีกาให้มีการเลือกตั้งสมาชิกสภาผู้แทนราษฎรกรุงเทพมหานคร เขตเลือกตั้งที่ ๑๒ แทนตำแหน่งที่ว่าง พ.ศ. ๒๕๕๖" volume="130" page="1-2" issue="45 ก" uri="2556/A/045/1.PDF" publication="2013-05-25" countersignedby="ยิ่งลักษณ์ ชินวัตร" countersignedbyfunction="PrimeMinister" sign="2013-05-25" />
  <entry description="Call for by-election in 8 constituencies" title="พระราชกฤษฎีกาให้มีการเลือกตั้งสมาชิกสภาผู้แทนราษฎรกรุงเทพมหานคร เขตเลือกตั้งที่ ๗ เขตเลือกตั้งที่ ๒๖ เขตเลือกตั้งที่ ๒๙ จังหวัดชุมพร เขตเลือกตั้งที่ ๑ จังหวัดตรัง เขตเลือกตั้งที่ ๒ จังหวัดนครศรีธรรมราช เขตเลือกตั้งที่ ๓ จังหวัดสงขลา เขตเลือกตั้งที่ ๖ และจังหวัดสุราษฎร์ธานี เขตเลือกตั้งที่ ๒ แทนตำแหน่งที่ว่าง พ.ศ. ๒๕๕๖" volume="130" page="1-3" issue="112 ก" uri="2556/A/112/1.PDF" publication="2013-11-27" countersignedby="ยิ่งลักษณ์ ชินวัตร" countersignedbyfunction="PrimeMinister" sign="2013-11-27" />
  <entry description="Announcement of election date for by-election in 8 constituencies" title="ประกาศคณะกรรมการการเลือกตั้ง เรื่อง การสมัครรับเลือกตั้งสมาชิกสภาผู้แทนราษฎรแทนตำแหน่งที่ว่าง" volume="130" page="5-6" issue="114 ก" uri="2556/A/114/5.PDF" publication="2013-12-03" sign="2013-11-28" signedby="อภิชาติ สุขัคคานนท์" signedbyfunction="ElectionCommissionPresident" />

  <!-- MP endorsements -->
  <entry description="Endorsement of party-list members of parliament" title="ประกาศคณะกรรมการการเลือกตั้ง เรื่อง ผลการเลือกตั้งสมาชิกสภาผู้แทนราษฎรแบบบัญชีรายชื่อ" subtitle="จำนวน ๑๐๙ คน ๑.นายยงยุทธ วิชัยดิษฐ ฯลฯ" volume="128" page="6-10" issue="58 ก" uri="2554/A/058/6.PDF" publication="2011-07-21" sign="2011-07-12" signedby="อภิชาติ สุขัคคานนท์" signedbyfunction="ElectionCommissionPresident" />
  <entry description="Endorsement of party-list members of parliament, part 2" title="ประกาศคณะกรรมการการเลือกตั้ง เรื่อง ผลการเลือกตั้งสมาชิกสภาผู้แทนราษฎรแบบบัญชีรายชื่อ  (ครั้งที่ ๒)" volume="128" page="6" issue="59 ก" uri="2554/A/059/6.PDF" publication="2011-07-27" sign="2011-07-19" signedby="อภิชาติ สุขัคคานนท์" signedbyfunction="ElectionCommissionPresident" />
  <entry description="Endorsement of party-list members of parliament, part 3" title="ประกาศคณะกรรมการการเลือกตั้ง เรื่อง ผลการเลือกตั้งสมาชิกสภาผู้แทนราษฎรแบบบัญชีรายชื่อ  (ครั้งที่ ๓)" volume="128" page="10" issue="59 ก" uri="2554/A/059/10.PDF" publication="2011-07-27" sign="2011-07-21" signedby="อภิชาติ สุขัคคานนท์" signedbyfunction="ElectionCommissionPresident" />
  <entry description="Endorsement of party-list members of parliament, part 4" title="ประกาศคณะกรรมการการเลือกตั้ง เรื่อง ผลการเลือกตั้งสมาชิกสภาผู้แทนราษฎรแบบบัญชีรายชื่อ (ครั้งที่ ๔)" volume="128" page="10" issue="60 ก" uri="2554/A/060/10.PDF" publication="2011-07-28" sign="2011-07-27" signedby="อภิชาติ สุขัคคานนท์" signedbyfunction="ElectionCommissionPresident" />
  <entry description="Endorsement of party-list members of parliament, part 5" title="ประกาศคณะกรรมการการเลือกตั้ง เรื่อง ผลการเลือกตั้งสมาชิกสภาผู้แทนราษฎรแบบบัญชีรายชื่อ (ครั้งที่ ๕)" subtitle="นายจตุพร พรหมพันธุ์" volume="128" page="18" issue="63 ก" uri="2554/A/063/18.PDF" publication="2011-08-05" sign="2011-08-01" signedby="อภิชาติ สุขัคคานนท์" signedbyfunction="ElectionCommissionPresident" />

  <entry description="Endorsement of constituency members of parliament" title="ประกาศคณะกรรมการการเลือกตั้ง เรื่อง ผลการเลือกตั้งสมาชิกสภาผู้แทนราษฎรแบบแบ่งเขตเลือกตั้ง" subtitle="จำนวน ๒๔๙ คน ๑.นางเจิมมาศ จึงเลิศศิริ ฯลฯ" volume="128" page="11-25" issue="58 ก" uri="2554/A/058/11.PDF" publication="2011-07-21" sign="2011-07-12" signedby="อภิชาติ สุขัคคานนท์" signedbyfunction="ElectionCommissionPresident" />
  <entry description="Endorsement of constituency members of parliament, part 2" title="ประกาศคณะกรรมการการเลือกตั้ง เรื่อง ผลการเลือกตั้งสมาชิกสภาผู้แทนราษฎรแบบแบ่งเขตเลือกตั้ง (ครั้งที่ ๒)" volume="128" page="4-5" issue="59 ก" uri="2554/A/059/4.PDF" publication="2011-07-19" sign="2011-07-19" signedby="อภิชาติ สุขัคคานนท์" signedbyfunction="ElectionCommissionPresident" />
  <entry description="Endorsement of constituency members of parliament, part 3" title="ประกาศคณะกรรมการการเลือกตั้ง เรื่อง ผลการเลือกตั้งสมาชิกสภาผู้แทนราษฎรแบบแบ่งเขตเลือกตั้ง (ครั้งที่ ๓)" volume="128" page="7-9" issue="59 ก" uri="2554/A/059/7.PDF" publication="2011-07-27" sign="2011-07-21" signedby="อภิชาติ สุขัคคานนท์" signedbyfunction="ElectionCommissionPresident" />
  <entry description="Endorsement of constituency members of parliament, part 4" title="ประกาศคณะกรรมการการเลือกตั้ง เรื่อง ผลการเลือกตั้งสมาชิกสภาผู้แทนราษฎรแบบแบ่งเขตเลือกตั้ง (ครั้งที่ ๔)" volume="128" page="11-17" issue="60 ก" uri="2554/A/060/11.PDF" publication="2011-07-28" sign="2011-07-27" signedby="อภิชาติ สุขัคคานนท์" signedbyfunction="ElectionCommissionPresident" />
  <entry description="Endorsement of constituency members of parliament, part 5" title="ประกาศคณะกรรมการการเลือกตั้ง เรื่อง ผลการเลือกตั้งสมาชิกสภาผู้แทนราษฎรแบบแบ่งเขตเลือกตั้ง (ครั้งที่ ๕)" subtitle="นายอับดุลการิม เด็งระกีนา นายจักรวาล ชัยวิรัตน์นุกูล นายสมคิด บาลไธสง" volume="128" page="17" issue="63 ก" uri="2554/A/063/17.PDF" publication="2011-08-05" sign="2011-08-01" signedby="อภิชาติ สุขัคคานนท์" signedbyfunction="ElectionCommissionPresident" />

  <entry description="Endorsement of by-election result" title="ประกาศคณะกรรมการการเลือกตั้ง เรื่อง ผลการเลือกตั้งสมาชิกสภาผู้แทนราษฎรแบบแบ่งเขตเลือกตั้ง" subtitle="จังหวัดปทุมธานี นายเกียรติศักดิ์ ส่องแสง พรรคประชาธิปัตย์" volume="129" page="27" issue="44 ก" uri="2555/A/044/27.PDF" publication="2012-05-23" sign="2012-05-17" signedby="อภิชาติ สุขัคคานนท์" signedbyfunction="ElectionCommissionPresident" />
  <entry description="Endorsement of by-election result (Chiang Mai constituency 3)" title="ประกาศคณะกรรมการการเลือกตั้ง เรื่อง ผลการเลือกตั้งสมาชิกสภาผู้แทนราษฎรแบบแบ่งเขตเลือกตั้ง" subtitle="จังหวัดเชียงใหม่ นายเกษม นิมมลรัตน์ พรรคเพื่อไทย" volume="129" page="23" issue="54 ก" uri="2555/A/054/23.PDF" publication="2012-06-20" sign="2012-06-13" signedby="อภิชาติ สุขัคคานนท์" signedbyfunction="ElectionCommissionPresident" />
  <entry description="Endorsement of by-election result" title="ประกาศคณะกรรมการการเลือกตั้ง เรื่อง ผลการเลือกตั้งสมาชิกสภาผู้แทนราษฎรแบบแบ่งเขตเลือกตั้ง" subtitle="จังหวัดลำพูน นายรังสรรค์ มณีรัตน์ พรรคเพื่อไทย" volume="129" page="62" issue="92 ก" uri="2555/A/092/62.PDF" publication="2012-09-28" sign="2012-09-25" signedby="อภิชาติ สุขัคคานนท์" signedbyfunction="ElectionCommissionPresident" />
  <entry description="Endorsement of by-election result (Chon Buri constituency 2)" title="ประกาศคณะกรรมการการเลือกตั้ง เรื่อง ผลการเลือกตั้งสมาชิกสภาผู้แทนราษฎรแบบแบ่งเขตเลือกตั้ง" subtitle="จังหวัดชลบุรี เขตเลือกตั้งที่ ๒ นายอุกฤษณ์ ตั๊นสวัสดิ์ พรรคพลังชล" volume="130" page="20" issue="14 ก" uri="2556/A/014/20.PDF" publication="2013-02-08" sign="2013-02-05" signedby="อภิชาติ สุขัคคานนท์" signedbyfunction="ElectionCommissionPresident" />
  <entry description="Endorsement of by-election result (Lopburi constituency 4)" title="ประกาศคณะกรรมการการเลือกตั้ง เรื่อง ผลการเลือกตั้งสมาชิกสภาผู้แทนราษฎรแบบแบ่งเขตเลือกตั้ง" subtitle="จังหวัดลพบุรี เขตเลือกตั้งที่ ๔ นายพหล วรปัญญา พรรคเพื่อไทย" volume="130" page="41" issue="19 ก" uri="2556/A/019/41.PDF" publication="2013-02-28" sign="2013-02-19" signedby="อภิชาติ สุขัคคานนท์" signedbyfunction="ElectionCommissionPresident" />
  <entry description="Endorsement of by-election result (Chiang Mai constituency 3)" title="ประกาศคณะกรรมการการเลือกตั้ง เรื่อง ผลการเลือกตั้งสมาชิกสภาผู้แทนราษฎรแบบแบ่งเขตเลือกตั้ง" subtitle="จังหวัดเชียงใหม่ เขตเลือกตั้งที่ ๓" volume="130" page="17" issue="43 ก" uri="2556/A/043/17.PDF" publication="2013-05-21" sign="2013-05-15" signedby="อภิชาติ สุขัคคานนท์" signedbyfunction="ElectionCommissionPresident" />
  <entry description="Endorsement of by-election result (Bangkok constituency 12)" title="ประกาศคณะกรรมการการเลือกตั้ง เรื่อง ผลการเลือกตั้งสมาชิกสภาผู้แทนราษฎรแบบแบ่งเขตเลือกตั้ง" subtitle="กรุงเทพมหานคร เขตเลือกตั้งที่ ๑๒ นายแทนคุณ จิตต์อิสระ พรรคประชาธิปัตย์" volume="130" page="7" issue="66 ก" uri="2556/A/066/7.PDF" publication="2013-07-25" sign="2013-07-16" signedby="อภิชาติ สุขัคคานนท์" signedbyfunction="ElectionCommissionPresident" />

  <entry description="Endorsement of move-up party-list member of parliament" title="ประกาศสภาผู้แทนราษฎร เรื่อง ให้ผู้มีชื่ออยู่ในลำดับถัดไปในบัญชีรายชื่อของพรรคการเมืองเลื่อนขึ้นมาเป็นสมาชิกสภาผู้แทนราษฎรแทนตำแหน่งที่ว่าง" subtitle="นายดนุพร ปุณณกันต์" volume="128" page="5" issue="พิเศษ 96 ง" uri="2554/E/096/5.PDF" publication="2011-08-25" sign="2011-08-23" signedby="สมศักดิ์ เกียรติสุรนนท์" signedbyfunction="SpeakerOfParliament" />
  <entry description="Endorsement of move-up party-list member of parliament" title="ประกาศสภาผู้แทนราษฎร เรื่อง ให้ผู้มีชื่ออยู่ในลำดับถัดไปในบัญชีรายชื่อของพรรคการเมืองเลื่อนขึ้นมาเป็นสมาชิกสภาผู้แทนราษฎรแทนตำแหน่งที่ว่าง" subtitle="นายยุรนันท์ ภมรมนตรี" volume="128" page="6" issue="พิเศษ 96 ง" uri="2554/E/096/6.PDF" publication="2011-08-25" sign="2011-08-25" signedby="สมศักดิ์ เกียรติสุรนนท์" signedbyfunction="SpeakerOfParliament" />
  <entry description="Endorsement of move-up party-list member of parliament" title="ประกาศสภาผู้เทนราษฎร เรื่อง ให้ผู้มีชื่ออยู่ในลำดับถัดไปในบัญชีรายชื่อของพรรคการเมืองเลื่อนขึ้นมาเป็นสมาชิกสภาผู้เทนราษฎรแทนตำแหน่งที่ว่าง" subtitle="นางบุศริณธญ์ วรพัฒนานันน์" volume="128" page="25" issue="พิเศษ 124 ง" uri="2554/E/124/25.PDF" publication="2011-10-17" sign="2011-10-14" signedby="สมศักดิ์ เกียรติสุรนนท์" signedbyfunction="SpeakerOfParliament" />
  <entry description="Endorsement of move-up party-list member of parliament" title="ประกาศสภาผู้แทนราษฎร เรื่อง ให้ผู้มีชื่ออยู่ในลำดับถัดไปในบัญชีรายชื่อของพรรคการเมืองเลื่อนขึ้นมาเป็นสมาชิกสภาผู้แทนราษฎรแทนตำแหน่งที่ว่าง" subtitle="นายกิตติศักดิ์ หัตถสงเคราะห์" volume="128" page="3" issue="พิเศษ 127 ง" uri="2554/E/127/3.PDF" publication="2011-10-21" sign="2011-10-19" signedby="สมศักดิ์ เกียรติสุรนนท์" signedbyfunction="SpeakerOfParliament" />
  <entry description="Endorsement of move-up party-list member of parliament" title="ประกาศสภาผู้แทนราษฎร เรื่อง ให้ผู้มีชื่ออยู่ในลำดับถัดไปในบัญชีรายชื่อของพรรคการเมืองเลื่อนขึ้นมาเป็นสมาชิกสภาผู้เทนราษฎรแทนตำแหน่งที่ว่าง" subtitle="นางอุดมรัตน์ อาภรณ์รัตน์" volume="128" page="8" issue="พิเศษ 128 ง" uri="2554/E/128/8.PDF" publication="2011-10-26" sign="2011-10-26" signedby="สมศักดิ์ เกียรติสุรนนท์" signedbyfunction="SpeakerOfParliament" />
  <entry description="Endorsement of move-up party-list member of parliament" title="ประกาศสภาผู้แทนราษฎร เรื่อง ให้ผู้มีชื่ออยู่ในลำดับถัดไปในบัญชีรายชื่อของพรรคการเมืองเลื่อนขึ้นมาเป็นสมาชิกสภาผู้แทนราษฎรแทนตำแหน่งที่ว่าง" subtitle="นายธวัชชัย สุทธิบงกช" volume="129" page="2" issue="พิเศษ 29 ง" uri="2555/E/029/2.PDF" publication="2012-02-04" sign="2012-02-03" signedby="สมศักดิ์ เกียรติสุรนนท์" signedbyfunction="SpeakerOfParliament" />
  <entry description="Endorsement of move-up party-list member of parliament" title="ประกาศสภาผู้แทนราษฎร เรื่อง ให้ผู้มีชื่ออยู่ในลำดับถัดไปในบัญชีรายชื่อของพรรคการเมืองเลื่อนขึ้นมาเป็นสมาชิกสภาผู้แทนราษฎรแทนตำแหน่งที่ว่าง" subtitle="นายชวลิต วิชยสุทธิ์" volume="129" page="1" issue="พิเศษ 29 ง" uri="2555/E/029/1.PDF" publication="2012-02-04" sign="2012-02-03" signedby="สมศักดิ์ เกียรติสุรนนท์" signedbyfunction="SpeakerOfParliament" />
  <entry description="Endorsement of move-up party-list member of parliament" title="ประกาศสภาผู้แทนราษฎร เรื่อง ให้ผู้มีชื่ออยู่ในลำดับถัดไปในบัญชีรายชื่อของพรรคการเมืองเลื่อนขึ้นมาเป็นสมาชิกสภาผู้แทนราษฎรแทนตำแหน่งที่ว่าง" volume="129" page="9" issue="พิเศษ 80 ง" uri="2555/E/080/9.PDF" publication="2012-05-14" sign="2012-05-11" signedby="สมศักดิ์ เกียรติสุรนนท์" signedbyfunction="SpeakerOfParliament" />
  <entry description="Endorsement of move-up party-list member of parliament" title="ประกาศสภาผู้แทนราษฎร เรื่อง ให้ผู้มีชื่ออยู่ในลำดับถัดไปในบัญชีรายชื่อของพรรคการเมืองเลื่อนขึ้นมาเป็นสมาชิกสภาผู้แทนราษฎรแทนตำแหน่งที่ว่าง" subtitle="ลำดับที่ ๗๐ พรรคเพื่อไทย ๑.นายสรรพภัญญู ศิริไปล์" volume="129" page="16" issue="พิเศษ 84 ง" uri="2555/E/084/16.PDF" publication="2012-05-23" sign="2012-05-23" signedby="สมศักดิ์ เกียรติสุรนนท์" signedbyfunction="SpeakerOfParliament" />
  <entry description="Endorsement of move-up party-list member of parliament" title="ประกาศสภาผู้แทนราษฎร เรื่อง ให้ผู้มีชื่ออยู่ในลำดับถัดไปในบัญชีรายชื่อของพรรคการเมืองเลื่อนขึ้นมาเป็นสมาชิกสภาผู้เทนราษฎรแทนตำแหน่งที่ว่าง" subtitle="นายสมเพชร แต่งงาม" volume="129" page="8" issue="พิเศษ 121 ง" uri="2555/E/121/8.PDF" publication="2012-08-01" sign="2012-08-01" signedby="สมศักดิ์ เกียรติสุรนนท์" signedbyfunction="SpeakerOfParliament" />
  <entry description="Endorsement of move-up party-list member of parliament" title="ประกาศสภาผู้แทนราษฎร เรื่อง ให้ผู้มีชื่ออยู่ในลำดับถัดไปในบัญชีรายชื่อของพรรคการเมืองเลื่อนขึ้นมาเป็นสมาชิกสภาผู้แทนราษฎรแทนตำแหน่งที่ว่าง" subtitle="นางสาวมาลินี อินฉัตร" volume="129" page="37" issue="พิเศษ 153 ง" uri="2555/E/153/37.PDF" publication="2012-10-08" sign="2012-10-05" signedby="สมศักดิ์ เกียรติสุรนนท์" signedbyfunction="SpeakerOfParliament" />
  <entry description="Endorsement of move-up party-list member of parliament" title="ประกาศสภาผู้แทนราษฎร เรื่อง ให้ผู้มีชื่ออยู่ในลำดับถัดไปในบัญชีรายชื่อของพรรคการเมือง เลื่อนขึ้นมาเป็นสมาชิกสภาผู้แทนราษฎรแทนตำแหน่งที่ว่าง" subtitle="นายชินวัฒน์ หาบุญพาด" volume="129" page="41" issue="พิเศษ 167 ง" uri="2555/E/167/41.PDF" publication="2012-11-02" sign="2012-11-01" signedby="สมศักดิ์ เกียรติสุรนนท์" signedbyfunction="SpeakerOfParliament" />
  <entry description="Endorsement of move-up party-list member of parliament" title="ประกาศสภาผู้แทนราษฎร เรื่อง ให้ผู้มีชื่ออยู่ในลำดับถัดไปในบัญชีรายชื่อของพรรคการเมือง เลื่อนขึ้นมาเป็นสมาชิกสภาผู้แทนราษฎรแทนตำแหน่งที่ว่าง" subtitle="นายเอกธนัช อินทร์รอด" volume="129" page="42" issue="พิเศษ 167 ง" uri="2555/E/167/42.PDF" publication="2012-11-02" sign="2012-11-02" signedby="สมศักดิ์ เกียรติสุรนนท์" signedbyfunction="SpeakerOfParliament" />
  <entry description="Endorsement of move-up party-list member of parliament" title="ประกาศสภาผู้เทนราษฎร เรื่อง ให้ผู้มีชื่ออยู่ในลำดับถัดไปในบัญชีรายชื่อของพรรคการเมืองเลื่อนขึ้นมาเป็นสมาชิกสภาผู้แทนราษฎรแทนตำแหน่งที่ว่าง" subtitle="นายประดิษฐ์ ภัทรประสิทธิ์" volume="130" page="11" issue="พิเศษ 10 ง" uri="2556/E/010/11.PDF" publication="2013-01-24" sign="2013-01-13" signedby="สมศักดิ์ เกียรติสุรนนท์" signedbyfunction="SpeakerOfParliament" />
  <entry description="Endorsement of move-up party-list member of parliament" title="ประกาศสภาผู้แทนราษฎร เรื่อง ให้ผู้มีชื่ออยู่ในลำดับถัดไปในบัญชีรายชื่อของพรรคการเมืองเลื่อนขึ้นมาเป็นสมาชิกสภาผู้แทนราษฎรแทนตำแหน่งที่ว่าง" subtitle="นายฐนนท์ศรณ์ เลิศฤทธิ์ศิริกุล" volume="130" page="14" issue="พิเศษ 24 ง" uri="2556/E/024/14.PDF" publication="2013-02-20" sign="2013-02-20" signedby="สมศักดิ์ เกียรติสุรนนท์" signedbyfunction="SpeakerOfParliament" />
  <entry description="Endorsement of move-up party-list member of parliament" title="ประกาศสภาผู้แทนราษฎร เรื่อง ให้ผู้มีชื่ออยู่ในลำดับถัดไปในบัญชีรายชื่อของพรรคการเมืองเลื่อนขึ้นมาเป็นสมาชิกสภาผู้แทนราษฎรแทนตำแหน่งที่ว่าง" subtitle="นายจุฤทธิ์ ลักษณวิศิษฏ์" volume="130" page="33" issue="พิเศษ 28 ง" uri="2556/E/028/33.PDF" publication="2013-03-01" sign="2013-03-01" signedby="สมศักดิ์ เกียรติสุรนนท์" signedbyfunction="SpeakerOfParliament" />
  <entry description="Endorsement of move-up party-list member of parliament" title="ประกาศสภาผู้เทนราษฎร เรื่อง ให้ผู้มีชื่ออยู่ในลำดับถัดไปในบัญชีรายชื่อของพรรคการเมืองเลื่อนขึ้นมาเป็นสมาชิกสภาผู้แทนราษฎรแทนตำแหน่งที่ว่าง" subtitle="นายอิสรา สุนทรวัฒน์" volume="130" page="21" issue="พิเศษ 39 ง" uri="2556/E/039/21.PDF" publication="2013-03-26" sign="2013-03-25" signedby="สมศักดิ์ เกียรติสุรนนท์" signedbyfunction="SpeakerOfParliament" />
  <entry description="Endorsement of move-up party-list member of parliament" title="ประกาศสภาผู้แทนราษฎร เรื่อง ให้ผู้มีชื่ออยู่ในลำดับถัดไปในบัญชีรายชื่อของพรรคการเมืองเลื่อนขึ้นมาเป็นสมาชิกสภาผู้แทนราษฎร แทนตำแหน่งที่ว่าง" subtitle="นายชวนนท์ อินทรโกมาลย์สุต" volume="130" page="42" issue="พิเศษ 43 ง" uri="2556/E/043/42.PDF" publication="2013-04-03" sign="2013-04-01" signedby="สมศักดิ์ เกียรติสุรนนท์" signedbyfunction="SpeakerOfParliament" />
  <entry description="Endorsement of move-up party-list member of parliament" title="ประกาศสภาผู้แทนราษฎร เรื่อง ให้ผู้มีชื่ออยู่ในลำดับถัดไปในบัญชีรายชื่อของพรรคการเมืองเลื่อนขึ้นมาเป็นสมาชิกสภาผู้แทนราษฎรแทนตำแหน่งที่ว่าง" subtitle="นายถิรชัย วุฒิธรรม" volume="130" page="55" issue="พิเศษ 63 ง" uri="2556/E/063/55.PDF" publication="2013-05-28" sign="2013-05-27" signedby="เจริญ จรรย์โกมล" signedbyfunction="DeputySpeakerOfParliament" />
  <entry description="Endorsement of move-up party-list member of parliament" title="ประกาศสภาผู้แทนราษฎร เรื่อง ให้ผู้มีชื่ออยู่ในลำดับถัดไปในบัญชีรายชื่อของพรรคการเมืองเลื่อนขึ้นมาเป็นสมาชิกสภาผู้แทนราษฎรแทนตำแหน่งที่ว่าง" volume="130" page="24" issue="พิเศษ 72 ง" uri="2556/E/072/24.PDF" publication="2013-06-17" sign="2013-06-14" signedby="สมศักดิ์ เกียรติสุรนนท์" signedbyfunction="SpeakerOfParliament" />
  <entry description="Endorsement of move-up party-list member of parliament" title="ประกาศสภาผู้แทนราษฎร เรื่อง ให้ผู้มีชื่ออยู่ในลำดับถัดไปในบัญชีรายชื่อของพรรคการเมือง เลื่อนขึ้นมาเป็นสมาชิกสภาผู้แทนราษฎรแทนตำแหน่งที่ว่าง" subtitle="นางมณทิพย์ ศรีรัตนา" volume="130" page="36" issue="พิเศษ 158 ง" uri="2556/E/158/36.PDF" publication="2013-11-14" sign="2013-11-13" signedby="สมศักดิ์ เกียรติสุรนนท์" signedbyfunction="SpeakerOfParliament" />

  <entry description="Call for vote recount in Yala Constituency 2" title="คำสั่งคณะกรรมการการเลือกตั้ง ที่ ๒๒๖/๒๕๕๔ เรื่อง ให้มีการนับคะแนนเลือกตั้งสมาชิกสภาผู้แทนราษฎรจังหวัดยะลา เขตเลือกตั้งที่ ๒ ใหม่" volume="128" page="18-20" issue="60 ก" uri="2554/A/060/18.PDF" publication="2011-07-28" sign="2011-07-27" signedby="อภิชาติ สุขัคคานนท์" signedbyfunction="ElectionCommissionPresident" />

  <!-- Parliament session -->
  <entry description="Act to open parliament session" title="พระราชกฤษฎีกาเรียกประชุมรัฐสภา พ.ศ. ๒๕๕๔" volume="128" page="1" issue="61 ก" uri="2554/A/061/1.PDF" publication="2011-07-29" sign="2011-07-29" countersignedby="อภิสิทธิ์ เวชชาชีวะ" countersignedbyfunction="PrimeMinister" />

  <!-- Cabinet -->
  <entry description="Announcement on endorsement of cabinet members" title="พระบรมราชโองการประกาศแต่งตั้งรัฐมนตรี" subtitle="รัฐบาลนางสาวยิ่งลักษณ์ ชินวัตร" volume="128" page="1-3" issue="พิเศษ 88 ง" uri="2554/E/088/1.PDF" publication="2011-08-09" countersignedby="ยิ่งลักษณ์ ชินวัตร" countersignedbyfunction="PrimeMinister" sign="2011-08-09" />
  <entry description="Announcement on endorsement of cabinet members, 2nd cabinet" title="พระบรมราชโองการให้รัฐมนตรีพ้นจากความเป็นรัฐมนตรีและแต่งตั้งรัฐมนตรี" subtitle="รัฐบาลนางสาวยิ่งลักษณ์ ชินวัตร ๒" volume="129" page="1-4" issue="พิเศษ 19 ง" uri="2555/E/019/1.PDF" publication="2012-01-18" countersignedby="ยิ่งลักษณ์ ชินวัตร" countersignedbyfunction="PrimeMinister" sign="2012-01-18" />
  <entry description="Announcement on endorsement of cabinet members, 3rd cabinet" title="พระบรมราชโองการ ประกาศให้รัฐมนตรีพ้นจากความเป็นรัฐมนตรีและแต่งตั้งรัฐมนตรี [รัฐบาลนางสาวยิ่งลักษณ์ ชินวัตร ๓]" volume="129" page="1-4" issue="พิเศษ 164 ง" uri="2555/E/164/1.PDF" publication="2012-10-28" countersignedby="ยิ่งลักษณ์ ชินวัตร" countersignedbyfunction="PrimeMinister" sign="2012-10-27" />

  <!-- Dissolution -->
  <entry description="Dissolution of parliament" title="พระราชกฤษฎีกายุบสภาผู้แทนราษฎร พ.ศ. ๒๕๕๖" volume="130" page="1-2" issue="115 ก" uri="2556/A/115/1.PDF" publication="2013-12-09" countersignedby="ยิ่งลักษณ์ ชินวัตร" countersignedbyfunction="PrimeMinister" sign="2012-12-09" />

  <!-- Party list candidates -->
  <entry title="ประกาศคณะกรรมการการเลือกตั้ง เรื่อง รายชื่อผู้สมัครรับเลือกตั้งสมาชิกสภาผู้แทนราษฎรแบบบัญชีรายชื่อ" subtitle="พรรคชีวิตที่ดีกว่า" volume="128" page="110" issue="49 ก" uri="2554/A/049/110.PDF" publication="2011-06-15" />
  <entry title="ประกาศคณะกรรมการการเลือกตั้ง เรื่อง รายชื่อผู้สมัครรับเลือกตั้งสมาชิกสภาผู้แทนราษฎรแบบบัญชีรายชื่อ" subtitle="พรรคมาตุภูมิ" volume="128" page="106" issue="49 ก" uri="2554/A/049/106.PDF" publication="2011-06-15" />
  <entry title="ประกาศคณะกรรมการการเลือกตั้ง เรื่อง รายชื่อผู้สมัครรับเลือกตั้งสมาชิกสภาผู้แทนราษฎรแบบบัญชีรายชื่อ" subtitle="พรรคพลังสังคมไทย" volume="128" page="111" issue="49 ก" uri="2554/A/049/111.PDF" publication="2011-06-15" />
  <entry title="ประกาศคณะกรรมการการเลือกตั้ง เรื่อง รายชื่อผู้สมัครรับเลือกตั้งสมาชิกสภาผู้แทนราษฎรแบบบัญชีรายชื่อ" subtitle="พรรคมหาชน" volume="128" page="113" issue="49 ก" uri="2554/A/049/113.PDF" publication="2011-06-15" />
  <entry title="ประกาศคณะกรรมการการเลือกตั้ง เรื่อง รายชื่อผู้สมัครรับเลือกตั้งสมาชิกสภาผู้แทนราษฎรแบบบัญชีรายชื่อ" subtitle="พรรคเพื่อประชาชนไทย" volume="128" page="112" issue="49 ก" uri="2554/A/049/112.PDF" publication="2011-06-15" />
  <entry title="ประกาศคณะกรรมการการเลือกตั้ง เรื่อง รายชื่อผู้สมัครรับเลือกตั้งสมาชิกสภาผู้แทนราษฎรแบบบัญชีรายชื่อ" subtitle="พรรคเสรีนิยม" volume="128" page="100" issue="49 ก" uri="2554/A/049/100.PDF" publication="2011-06-15" />
  <entry title="ประกาศคณะกรรมการการเลือกตั้ง เรื่อง รายชื่อผู้สมัครรับเลือกตั้งสมาชิกสภาผู้แทนราษฎรแบบบัญชีรายชื่อ" subtitle="พรรคชาติไทยพัฒนา" volume="128" page="90" issue="49 ก" uri="2554/A/049/90.PDF" publication="2011-06-15" />
  <entry title="ประกาศคณะกรรมการการเลือกตั้ง เรื่อง รายชื่อผู้สมัครรับเลือกตั้งสมาชิกสภาผู้แทนราษฎรแบบบัญชีรายชื่อ" subtitle="พรรคชาติสามัคคี" volume="128" page="101" issue="49 ก" uri="2554/A/049/101.PDF" publication="2011-06-15" />
  <entry title="ประกาศคณะกรรมการการเลือกตั้ง เรื่อง รายชื่อผู้สมัครรับเลือกตั้งสมาชิกสภาผู้แทนราษฎรแบบบัญชีรายชื่อ" subtitle="พรรคกสิกรไทย" volume="128" page="105" issue="49 ก" uri="2554/A/049/105.PDF" publication="2011-06-15" />
  <entry title="ประกาศคณะกรรมการการเลือกตั้ง เรื่อง รายชื่อผู้สมัครรับเลือกตั้งสมาชิกสภาผู้แทนราษฎรแบบบัญชีรายชื่อ" subtitle="พรรคบำรุงเมือง" volume="128" page="103" issue="49 ก" uri="2554/A/049/103.PDF" publication="2011-06-15" />
  <entry title="ประกาศคณะกรรมการการเลือกตั้ง เรื่อง รายชื่อผู้สมัครรับเลือกตั้งสมาชิกสภาผู้แทนราษฎรแบบบัญชีรายชื่อ" subtitle="พรรคพลังชาวนาไทย" volume="128" page="139" issue="49 ก" uri="2554/A/049/139.PDF" publication="2011-06-15" />
  <entry title="ประกาศคณะกรรมการการเลือกตั้ง เรื่อง รายชื่อผู้สมัครรับเลือกตั้งสมาชิกสภาผู้แทนราษฎรแบบบัญชีรายชื่อ" subtitle="พรรคพลังคนกีฬา" volume="128" page="131" issue="49 ก" uri="2554/A/049/131.PDF" publication="2011-06-15" />
  <entry title="ประกาศคณะกรรมการการเลือกตั้ง เรื่อง รายชื่อผู้สมัครรับเลือกตั้งสมาชิกสภาผู้แทนราษฎรแบบบัญชีรายชื่อ" subtitle="พรรคไทยสร้างสรรค์" volume="128" page="140" issue="49 ก" uri="2554/A/049/140.PDF" publication="2011-06-15" />
  <entry title="ประกาศคณะกรรมการการเลือกตั้ง เรื่อง รายชื่อผู้สมัครรับเลือกตั้งสมาชิกสภาผู้แทนราษฎรแบบบัญชีรายชื่อ" subtitle="พรรคมหารัฐพัฒนา" volume="128" page="144" issue="49 ก" uri="2554/A/049/144.PDF" publication="2011-06-15" />
  <entry title="ประกาศคณะกรรมการการเลือกตั้ง เรื่อง รายชื่อผู้สมัครรับเลือกตั้งสมาชิกสภาผู้แทนราษฎรแบบบัญชีรายชื่อ" subtitle="พรรคเพื่อนเกษตรไทย" volume="128" page="141" issue="49 ก" uri="2554/A/049/141.PDF" publication="2011-06-15" />
  <entry title="ประกาศคณะกรรมการการเลือกตั้ง เรื่อง รายชื่อผู้สมัครรับเลือกตั้งสมาชิกสภาผู้แทนราษฎรแบบบัญชีรายชื่อ" subtitle="พรรครักแผ่นดิน" volume="128" page="115" issue="49 ก" uri="2554/A/049/115.PDF" publication="2011-06-15" />
  <entry title="ประกาศคณะกรรมการการเลือกตั้ง เรื่อง รายชื่อผู้สมัครรับเลือกตั้งสมาชิกสภาผู้แทนราษฎรแบบบัญชีรายชื่อ" subtitle="พรรคประชาชนชาวไทย" volume="128" page="114" issue="49 ก" uri="2554/A/049/114.PDF" publication="2011-06-15" />
  <entry title="ประกาศคณะกรรมการการเลือกตั้ง เรื่อง รายชื่อผู้สมัครรับเลือกตั้งสมาชิกสภาผู้แทนราษฎรแบบบัญชีรายชื่อ" subtitle="พรรคประชาสันติ" volume="128" page="116" issue="49 ก" uri="2554/A/049/116.PDF" publication="2011-06-15" />
  <entry title="ประกาศคณะกรรมการการเลือกตั้ง เรื่อง รายชื่อผู้สมัครรับเลือกตั้งสมาชิกสภาผู้แทนราษฎรแบบบัญชีรายชื่อ" subtitle="พรรคอาสามาตุภูมิ" volume="128" page="130" issue="49 ก" uri="2554/A/049/130.PDF" publication="2011-06-15" />
  <entry title="ประกาศคณะกรรมการการเลือกตั้ง เรื่อง รายชื่อผู้สมัครรับเลือกตั้งสมาชิกสภาผู้แทนราษฎรแบบบัญชีรายชื่อ" subtitle="พรรคความหวังใหม่" volume="128" page="120" issue="49 ก" uri="2554/A/049/120.PDF" publication="2011-06-15" />
  <entry title="ประกาศคณะกรรมการการเลือกตั้ง เรื่อง รายชื่อผู้สมัครรับเลือกตั้งสมาชิกสภาผู้แทนราษฎรแบบบัญชีรายชื่อ" subtitle="พรรคการเมืองใหม่" volume="128" page="87" issue="49 ก" uri="2554/A/049/87.PDF" publication="2011-06-15" />
  <entry title="ประกาศคณะกรรมการการเลือกตั้ง เรื่อง รายชื่อผู้สมัครรับเลือกตั้งสมาชิกสภาผู้แทนราษฎรแบบบัญชีรายชื่อ" subtitle="พรรคประชาธรรม" volume="128" page="33" issue="49 ก" uri="2554/A/049/33.PDF" publication="2011-06-15" />
  <entry title="ประกาศคณะกรรมการการเลือกตั้ง เรื่อง รายชื่อผู้สมัครรับเลือกตั้งสมาชิกสภาผู้แทนราษฎรแบบบัญชีรายชื่อ" subtitle="พรรคพลังชล" volume="128" page="31" issue="49 ก" uri="2554/A/049/31.PDF" publication="2011-06-15" />
  <entry title="ประกาศคณะกรรมการการเลือกตั้ง เรื่อง รายชื่อผู้สมัครรับเลือกตั้งสมาชิกสภาผู้แทนราษฎรแบบบัญชีรายชื่อ" subtitle="พรรคพลังมวลชน" volume="128" page="38" issue="49 ก" uri="2554/A/049/38.PDF" publication="2011-06-15" />
  <entry title="ประกาศคณะกรรมการการเลือกตั้ง เรื่อง รายชื่อผู้สมัครรับเลือกตั้งสมาชิกสภาผู้แทนราษฎรแบบบัญชีรายชื่อ" subtitle="พรรคดำรงไทย" volume="128" page="36" issue="49 ก" uri="2554/A/049/36.PDF" publication="2011-06-15" />
  <entry title="ประกาศคณะกรรมการการเลือกตั้ง เรื่อง รายชื่อผู้สมัครรับเลือกตั้งสมาชิกสภาผู้แทนราษฎรแบบบัญชีรายชื่อ" subtitle="พรรครักประเทศไทย" volume="128" page="29" issue="49 ก" uri="2554/A/049/29.PDF" publication="2011-06-15" />
  <entry title="ประกาศคณะกรรมการการเลือกตั้ง เรื่อง รายชื่อผู้สมัครรับเลือกตั้งสมาชิกสภาผู้แทนราษฎรแบบบัญชีรายชื่อ" subtitle="พรรคชาติพัฒนาเพื่อแผ่นดิน" volume="128" page="15" issue="49 ก" uri="2554/A/049/15.PDF" publication="2011-06-15" />
  <entry title="ประกาศคณะกรรมการการเลือกตั้ง เรื่อง รายชื่อผู้สมัครรับเลือกตั้งสมาชิกสภาผู้แทนราษฎรแบบบัญชีรายชื่อ" subtitle="พรรคเพื่อไทย" volume="128" page="5" issue="49 ก" uri="2554/A/049/5.PDF" publication="2011-06-15" />
  <entry title="ประกาศคณะกรรมการการเลือกตั้ง เรื่อง รายชื่อผู้สมัครรับเลือกตั้งสมาชิกสภาผู้แทนราษฎรแบบบัญชีรายชื่อ" subtitle="พรรคประชากรไทย" volume="128" page="27" issue="49 ก" uri="2554/A/049/27.PDF" publication="2011-06-15" />
  <entry title="ประกาศคณะกรรมการการเลือกตั้ง เรื่อง รายชื่อผู้สมัครรับเลือกตั้งสมาชิกสภาผู้แทนราษฎรแบบบัญชีรายชื่อ" subtitle="พรรคประชาธิปไตยใหม่" volume="128" page="26" issue="49 ก" uri="2554/A/049/26.PDF" publication="2011-06-15" />
  <entry title="ประกาศคณะกรรมการการเลือกตั้ง เรื่อง รายชื่อผู้สมัครรับเลือกตั้งสมาชิกสภาผู้แทนราษฎรแบบบัญชีรายชื่อ" subtitle="พรรคประชาธิปัตย์" volume="128" page="39" issue="49 ก" uri="2554/A/049/39.PDF" publication="2011-06-15" />
  <entry title="ประกาศคณะกรรมการการเลือกตั้ง เรื่อง รายชื่อผู้สมัครรับเลือกตั้งสมาชิกสภาผู้แทนราษฎรแบบบัญชีรายชื่อ" subtitle="พรรคแทนคุณแผ่นดิน" volume="128" page="80" issue="49 ก" uri="2554/A/049/80.PDF" publication="2011-06-15" />
  <entry title="ประกาศคณะกรรมการการเลือกตั้ง เรื่อง รายชื่อผู้สมัครรับเลือกตั้งสมาชิกสภาผู้แทนราษฎรแบบบัญชีรายชื่อ" subtitle="พรรคภูมิใจไทย" volume="128" page="70" issue="49 ก" uri="2554/A/049/70.PDF" publication="2011-06-15" />
  <entry title="ประกาศคณะกรรมการการเลือกตั้ง เรื่อง รายชื่อผู้สมัครรับเลือกตั้งสมาชิกสภาผู้แทนราษฎรแบบบัญชีรายชื่อ" subtitle="พรรคเครือข่ายชาวนาแห่งประเทศไทย" volume="128" page="84" issue="49 ก" uri="2554/A/049/84.PDF" publication="2011-06-15" />
  <entry title="ประกาศคณะกรรมการการเลือกตั้ง เรื่อง รายชื่อผู้สมัครรับเลือกตั้งสมาชิกสภาผู้แทนราษฎรแบบบัญชีรายชื่อ" subtitle="พรรคเพื่อฟ้าดิน" volume="128" page="83" issue="49 ก" uri="2554/A/049/83.PDF" publication="2011-06-15" />
  <entry title="ประกาศคณะกรรมการการเลือกตั้ง เรื่อง รายชื่อผู้สมัครรับเลือกตั้งสมาชิกสภาผู้แทนราษฎรแบบบัญชีรายชื่อ" subtitle="พรรคไทยเป็นไท" volume="128" page="68" issue="49 ก" uri="2554/A/049/68.PDF" publication="2011-06-15" />
  <entry title="ประกาศคณะกรรมการการเลือกตั้ง เรื่อง รายชื่อผู้สมัครรับเลือกตั้งสมาชิกสภาผู้แทนราษฎรแบบบัญชีรายชื่อ" subtitle="พรรครักษ์สันติ" volume="128" page="51" issue="49 ก" uri="2554/A/049/51.PDF" publication="2011-06-15" />
  <entry title="ประกาศคณะกรรมการการเลือกตั้ง เรื่อง รายชื่อผู้สมัครรับเลือกตั้งสมาชิกสภาผู้แทนราษฎรแบบบัญชีรายชื่อ" subtitle="พรรคไทยพอเพียง" volume="128" page="50" issue="49 ก" uri="2554/A/049/50.PDF" publication="2011-06-15" />
  <entry title="ประกาศคณะกรรมการการเลือกตั้ง เรื่อง รายชื่อผู้สมัครรับเลือกตั้งสมาชิกสภาผู้แทนราษฎรแบบบัญชีรายชื่อ" subtitle="พรรคกิจสังคม" volume="128" page="58" issue="49 ก" uri="2554/A/049/58.PDF" publication="2011-06-15" />
  <entry title="ประกาศคณะกรรมการการเลือกตั้ง เรื่อง รายชื่อผู้สมัครรับเลือกตั้งสมาชิกสภาผู้แทนราษฎรแบบบัญชีรายชื่อ" subtitle="พรรคไทยเป็นสุข" volume="128" page="57" issue="49 ก" uri="2554/A/049/57.PDF" publication="2011-06-15" />
  <entry title="ประกาศคณะกรรมการการเลือกตั้ง เรื่อง รายชื่อผู้สมัครรับเลือกตั้งสมาชิกสภาผู้แทนราษฎรแบบบัญชีรายชื่อ (เพิ่มเติม)" volume="128" page="15" issue="54 ก" uri="2554/A/054/15.PDF" publication="2011-07-04" />
</gazette>