<?xml version="1.0" encoding="utf-8" ?>
<entity type="Changwat" name="เชียงใหม่" english="Chiang Mai" geocode="50" >
  <entity type="Amphoe" name="เมืองเชียงใหม่" english="Mueang Chiang Mai" geocode="5001" >
    <entity type="Tambon" name="ศรีภูมิ" english="Si Phum" geocode="500101" />
    <entity type="Tambon" name="พระสิงห์" english="Phra Sing" geocode="500102" />
    <entity type="Tambon" name="หายยา" english="Haiya" geocode="500103" />
    <entity type="Tambon" name="ช้างม่อย" english="Chang Moi" geocode="500104" />
    <entity type="Tambon" name="ช้างคลาน" english="Chang Khlan" geocode="500105" />
    <entity type="Tambon" name="วัดเกต" english="Wat Ket" geocode="500106" />
    <entity type="Tambon" name="ช้างเผือก" english="Chang Phueak" geocode="500107" />
    <entity type="Tambon" name="สุเทพ" english="Suthep" geocode="500108" />
    <entity type="Tambon" name="แม่เหียะ" english="Mae Hia" geocode="500109" />
    <entity type="Tambon" name="ป่าแดด" english="Pa Daet" geocode="500110" />
    <entity type="Tambon" name="หนองหอย" english="Nong Hoi" geocode="500111" />
    <entity type="Tambon" name="ท่าศาลา" english="Tha Sala" geocode="500112" />
    <entity type="Tambon" name="หนองป่าครั่ง" english="Nong Pa Khrang" geocode="500113" />
    <entity type="Tambon" name="ฟ้าฮ่าม" english="Fa Ham" geocode="500114" />
    <entity type="Tambon" name="ป่าตัน" english="Pa Tan" geocode="500115" />
    <entity type="Tambon" name="สันผีเสื้อ" english="San Phi Suea" geocode="500116" />
  </entity>
  <entity type="Amphoe" name="จอมทอง" english="Chom Thong" geocode="5002" >
    <entity type="Tambon" name="ยางคราม" english="Yang Khram" geocode="500201" newgeocode="502403" />
    <entity type="Tambon" name="สองแคว" english="Song Khwae" geocode="500202" newgeocode="502402" />
    <entity type="Tambon" name="บ้านหลวง" english="Ban Luang" geocode="500203" />
    <entity type="Tambon" name="ข่วงเปา" english="Khuang Pao" geocode="500204" />
    <entity type="Tambon" name="สบเตี๊ยะ" english="Sop Tia" geocode="500205" />
    <entity type="Tambon" name="บ้านแปะ" english="Ban Pae" geocode="500206" />
    <entity type="Tambon" name="ดอยแก้ว" english="Doi Kaeo" geocode="500207" />
    <entity type="Tambon" name="ดอยหล่อ" english="Doi Lo" geocode="500208" newgeocode="502401" />
    <entity type="Tambon" name="แม่สอย" english="Mae Soi" geocode="500209" />
    <entity type="Tambon" name="สันติสุข" english="Santi Suk" geocode="500210" newgeocode="502404" />
  </entity>
  <entity type="Amphoe" name="แม่แจ่ม" english="Mae Chaem" geocode="5003" >
    <entity type="Tambon" name="ช่างเคิ่ง" english="Chang Khoeng" geocode="500301" />
    <entity type="Tambon" name="ท่าผา" english="Tha Pha" geocode="500302" />
    <entity type="Tambon" name="บ้านทับ" english="Ban Thap" geocode="500303" />
    <entity type="Tambon" name="แม่ศึก" english="Mae Suek" geocode="500304" />
    <entity type="Tambon" name="แม่นาจร" english="Mae Na Chon" geocode="500305" />
    <entity type="Tambon" name="บ้านจันทร์" english="Ban Chan" geocode="500306" />
    <entity type="Tambon" name="ปางหินฝน" english="Pang Hin Fon" geocode="500307" />
    <entity type="Tambon" name="กองแขก" english="Kong Khaek" geocode="500308" />
    <entity type="Tambon" name="แม่แดด" english="Mae Daet" geocode="500309" />
    <entity type="Tambon" name="แจ่มหลวง" english="Chaem Luang" geocode="500310" />
  </entity>
  <entity type="Amphoe" name="เชียงดาว" english="Chiang Dao" geocode="5004" >
    <entity type="Tambon" name="เชียงดาว" english="Chiang Dao" geocode="500401" />
    <entity type="Tambon" name="เมืองนะ" english="Mueang Na" geocode="500402" />
    <entity type="Tambon" name="เมืองงาย" english="Mueang Ngai" geocode="500403" />
    <entity type="Tambon" name="แม่นะ" english="Mae Na" geocode="500404" />
    <entity type="Tambon" name="เมืองคอง" english="Mueang Khong" geocode="500405" />
    <entity type="Tambon" name="ปิงโค้ง" english="Ping Khong" geocode="500406" />
    <entity type="Tambon" name="ทุ่งข้าวพวง" english="Thung Khao Phuang" geocode="500407" />
  </entity>
  <entity type="Amphoe" name="ดอยสะเก็ด" english="Doi Saket" geocode="5005" >
    <entity type="Tambon" name="เชิงดอย" english="Choeng Doi" geocode="500501" />
    <entity type="Tambon" name="สันปูเลย" english="San Pu Loei" geocode="500502" />
    <entity type="Tambon" name="ลวงเหนือ" english="Luang Nuea" geocode="500503" />
    <entity type="Tambon" name="ป่าป้อง" english="Pa Pong" geocode="500504" />
    <entity type="Tambon" name="สง่าบ้าน" english="Sa-nga Ban" geocode="500505" />
    <entity type="Tambon" name="ป่าลาน" english="Pa Lan" geocode="500506" />
    <entity type="Tambon" name="ตลาดขวัญ" english="Talat Khwan" geocode="500507" />
    <entity type="Tambon" name="สำราญราษฎร์" english="Samran Rat" geocode="500508" />
    <entity type="Tambon" name="แม่คือ" english="Mae Khue" geocode="500509" />
    <entity type="Tambon" name="ตลาดใหญ่" english="Talat Yai" geocode="500510" />
    <entity type="Tambon" name="แม่ฮ้อยเงิน" english="Mae Hoi Ngoen" geocode="500511" />
    <entity type="Tambon" name="แม่โป่ง" english="Mae Pong" geocode="500512" />
    <entity type="Tambon" name="ป่าเมี่ยง" english="Pa Miang" geocode="500513" />
    <entity type="Tambon" name="เทพเสด็จ" english="Thep Sadet" geocode="500514" />
  </entity>
  <entity type="Amphoe" name="แม่แตง" english="Mae Taeng" geocode="5006" >
    <entity type="Tambon" name="สันมหาพน" english="San Maha Phon" geocode="500601" />
    <entity type="Tambon" name="แม่แตง" english="Mae Taeng" geocode="500602" />
    <entity type="Tambon" name="ขี้เหล็ก" english="Khilek" geocode="500603" />
    <entity type="Tambon" name="ช่อแล" english="Cho Lae" geocode="500604" />
    <entity type="Tambon" name="แม่หอพระ" english="Mae Ho Phra" geocode="500605" />
    <entity type="Tambon" name="สบเปิง" english="Sop Poeng" geocode="500606" />
    <entity type="Tambon" name="บ้านเป้า" english="Ban Pao" geocode="500607" />
    <entity type="Tambon" name="สันป่ายาง" english="San Pa Yang" geocode="500608" />
    <entity type="Tambon" name="ป่าแป๋" english="Pa Pae" geocode="500609" />
    <entity type="Tambon" name="เมืองก๋าย" english="Mueang Kai" geocode="500610" />
    <entity type="Tambon" name="บ้านช้าง" english="Ban Chang" geocode="500611" />
    <entity type="Tambon" name="กื้ดช้าง" english="Kuet Chang" geocode="500612" />
    <entity type="Tambon" name="อินทขิล" english="Inthakhin" geocode="500613" />
    <entity type="Tambon" name="สมก๋าย" english="Som Kai" geocode="500614" />
  </entity>
  <entity type="Amphoe" name="แม่ริม" english="Mae Rim" geocode="5007" >
    <entity type="Tambon" name="ริมใต้" english="Rim Tai" geocode="500701" />
    <entity type="Tambon" name="ริมเหนือ" english="Rim Nuea" geocode="500702" />
    <entity type="Tambon" name="สันโป่ง" english="San Pong" geocode="500703" />
    <entity type="Tambon" name="ขี้เหล็ก" english="Khilek" geocode="500704" />
    <entity type="Tambon" name="สะลวง" english="Saluang" geocode="500705" />
    <entity type="Tambon" name="ห้วยทราย" english="Huai Sai" geocode="500706" >
      <entity type="Muban" geocode="50070605" name="บ้านหัวฝาย" english="Ban Hua Fai" oldname="บ้านเหล่า"  englishold="Ban Hua Fai"/>
    </entity>
    <entity type="Tambon" name="แม่แรม" english="Mae Raem" geocode="500707" />
    <entity type="Tambon" name="โป่งแยง" english="Pong Yaeng" geocode="500708" />
    <entity type="Tambon" name="แม่สา" english="Mae Sa" geocode="500709" />
    <entity type="Tambon" name="ดอนแก้ว" english="Don Kaeo" geocode="500710" />
    <entity type="Tambon" name="เหมืองแก้ว" english="Mueang Kaeo" geocode="500711" />
  </entity>
  <entity type="Amphoe" name="สะเมิง" english="Samoeng" geocode="5008" >
    <entity type="Tambon" name="สะเมิงใต้" english="Samoeng Tai" geocode="500801" />
    <entity type="Tambon" name="สะเมิงเหนือ" english="Samoeng Nuea" geocode="500802" />
    <entity type="Tambon" name="แม่สาบ" english="Mae Sap" geocode="500803" />
    <entity type="Tambon" name="บ่อแก้ว" english="Bo Kaeo" geocode="500804" />
    <entity type="Tambon" name="ยั้งเมิน" english="Yang Moen" geocode="500805" />
  </entity>
  <entity type="Amphoe" name="ฝาง" english="Fang" geocode="5009" >
    <entity type="Tambon" name="เวียง" english="Wiang" geocode="500901" />
    <entity type="Tambon" name="ปงตำ" english="Pong Tam" geocode="500902" newgeocode="502101" />
    <entity type="Tambon" name="ม่อนปิ่น" english="Mon Pin" geocode="500903" />
    <entity type="Tambon" name="แม่งอน" english="Mae Ngon" geocode="500904" />
    <entity type="Tambon" name="แม่สูน" english="Mae Sun" geocode="500905" />
    <entity type="Tambon" name="สันทราย" english="San Sai" geocode="500906" />
    <entity type="Tambon" name="ศรีดงเย็น" english="Si Dong Yen" geocode="500907" newgeocode="502102" />
    <entity type="Tambon" name="แม่ทะลบ" english="Mae Thalop" geocode="500908" newgeocode="502103" />
    <entity type="Tambon" name="หนองบัว" english="Nong Bua" geocode="500909" newgeocode="502104" />
    <entity type="Tambon" name="แม่คะ" english="Mae Kha" geocode="500910" />
    <entity type="Tambon" name="แม่ข่า" english="Mae Kha" geocode="500911" />
    <entity type="Tambon" name="โป่งน้ำร้อน" english="Pong Nam Ron" geocode="500912" />

    <entity type="Unknown" name="แม่นาวาง" english="Mae Na Wang" geocode="500995" newgeocode="501004" />
    <entity type="Unknown" name="แม่สาว" english="Mae Sao" geocode="500996" newgeocode="501002" />
    <entity type="Unknown" name="แม่อาย" english="Mae Ai" geocode="500997" newgeocode="501001" />
    <entity type="Unknown" name="ศรีดงเย็น" english="Si Dong Yen" geocode="500998" newgeocode="502102" />
    <entity type="Unknown" name="ปงตำ" english="Pong Tam" geocode="500999" newgeocode="502101" />
  </entity>
  <entity type="Amphoe" name="แม่อาย" english="Mae Ai" geocode="5010" >
    <entity type="Tambon" name="แม่อาย" english="Mae Ai" geocode="501001" />
    <entity type="Tambon" name="แม่สาว" english="Mae Sao" geocode="501002" />
    <entity type="Tambon" name="สันต้นหมื้อ" english="San Ton Mue" geocode="501003" />
    <entity type="Tambon" name="แม่นาวาง" english="Mae Na Wang" geocode="501004" >
      <entity type="Muban" geocode="50100407" name="บ้านห้วยคอกหมู" english="Ban Huay Khok Mu" />
      <entity type="Muban" geocode="50100414" name="บ้านแม่เมืองน้อย" english="Ban Mae Mueang Noi" />
    </entity>
    <entity type="Tambon" name="ท่าตอน" english="Tha Ton" geocode="501005" />
    <entity type="Tambon" name="บ้านหลวง" english="Ban Luang" geocode="501006" />
    <entity type="Tambon" name="มะลิกา" english="Malika" geocode="501007" />
  </entity>
  <entity type="Amphoe" name="พร้าว" english="Phrao" geocode="5011" >
    <entity type="Tambon" name="เวียง" english="Wiang" geocode="501101" />
    <entity type="Tambon" name="ทุ่งหลวง" english="Thung Luang" geocode="501102" />
    <entity type="Tambon" name="ป่าตุ้ม" english="Pa Tum" geocode="501103" />
    <entity type="Tambon" name="ป่าไหน่" english="Pa Nai" geocode="501104" />
    <entity type="Tambon" name="สันทราย" english="San Sai" geocode="501105" />
    <entity type="Tambon" name="บ้านโป่ง" english="Ban Pong" geocode="501106" />
    <entity type="Tambon" name="น้ำแพร่" english="Nam Phrae" geocode="501107" />
    <entity type="Tambon" name="เขื่อนผาก" english="Khuean Phak" geocode="501108" >
      <entity type="Muban" geocode="50110801" name="บ้านแพะพัฒนา" english="Ban Phae Phatthana" />
    </entity>
    <entity type="Tambon" name="แม่แวน" english="Mae Waen" geocode="501109" />
    <entity type="Tambon" name="แม่ปั๋ง" english="Mae Pang" geocode="501110" />
    <entity type="Tambon" name="โหล่งขอด" english="Long Khot" geocode="501111" />
  </entity>
  <entity type="Amphoe" name="สันป่าตอง" english="San Pa Tong" geocode="5012" >
    <entity type="Tambon" name="ยุหว่า" english="Yu Wa" geocode="501201" />
    <entity type="Tambon" name="สันกลาง" english="San Klang" geocode="501202" />
    <entity type="Tambon" name="ท่าวังพร้าว" english="Tha Wang Phrao" geocode="501203" />
    <entity type="Tambon" name="มะขามหลวง" english="Makham Luang" geocode="501204" />
    <entity type="Tambon" name="แม่ก๊า" english="Mae Ka" geocode="501205" />
    <entity type="Tambon" name="บ้านแม" english="Ban Mae" geocode="501206" />
    <entity type="Tambon" name="บ้านกลาง" english="Ban Klang" geocode="501207" />
    <entity type="Tambon" name="ทุ่งสะโตก" english="Thung Satok" geocode="501208" />
    <entity type="Tambon" name="ทุ่งปี้" english="Thung Pi" geocode="501209" newgeocode="502202" />
    <entity type="Tambon" name="ทุ่งต้อม" english="Thung Tom" geocode="501210" />
    <entity type="Tambon" name="บ้านกาด" english="Ban Kat" geocode="501211" newgeocode="502201" />
    <entity type="Tambon" name="แม่วิน" english="Mae Win" geocode="501212" newgeocode="502204" />
    <entity type="Tambon" name="ทุ่งรวงทอง" english="Thung Ruang Thong" geocode="501213" newgeocode="502203" />
    <entity type="Tambon" name="น้ำบ่อหลวง" english="Nam Bo Luang" geocode="501214" />
    <entity type="Tambon" name="มะขุนหวาน" english="Makhun Wan" geocode="501215" />
  </entity>
  <entity type="Amphoe" name="สันกำแพง" english="San Kamphaeng" geocode="5013" >
    <entity type="Tambon" name="สันกำแพง" english="San Kamphaeng" geocode="501301" />
    <entity type="Tambon" name="ทรายมูล" english="Sai Mun" geocode="501302" />
    <entity type="Tambon" name="ร้องวัวแดง" english="Rong Wua Daeng" geocode="501303" />
    <entity type="Tambon" name="บวกค้าง" english="Buak Khang" geocode="501304" />
    <entity type="Tambon" name="แช่ช้าง" english="Chae Chang" geocode="501305" />
    <entity type="Tambon" name="ออนใต้" english="On Tai" geocode="501306" />
    <entity type="Tambon" name="ออนเหนือ" english="On Nuea" geocode="501307" newgeocode="502301" />
    <entity type="Tambon" name="บ้านสหกรณ์" english="Ban Sahakon" geocode="501308" newgeocode="502303" />
    <entity type="Tambon" name="ห้วยแก้ว" english="Huai Kaeo" geocode="501309" newgeocode="502304" />
    <entity type="Tambon" name="แม่ปูคา" english="Mae Pu Kha" geocode="501310" />
    <entity type="Tambon" name="ห้วยทราย" english="Huai Sai" geocode="501311" />
    <entity type="Tambon" name="ต้นเปา" english="Ton Pao" geocode="501312" />
    <entity type="Tambon" name="สันกลาง" english="San Klang" geocode="501313" />
    <entity type="Tambon" name="แม่ทา" english="Mae Tha" geocode="501314" newgeocode="502305" />
    <entity type="Tambon" name="ทาเหนือ" english="Tha Nuea" geocode="501315" newgeocode="502306" />
    <entity type="Tambon" name="ออนกลาง" english="On Klang" geocode="501316" newgeocode="502302" />

    <entity type="Unknown" name="แม่วิน" english="Mae Win" geocode="501397" newgeocode="502204" />
    <entity type="Unknown" name="ทุ่งปี้" english="Thung Pi" geocode="501398" newgeocode="502202" />
    <entity type="Unknown" name="บ้านกาด" english="Ban Kat" geocode="501399" newgeocode="502201" />
  </entity>
  <entity type="Amphoe" name="สันทราย" english="San Sai" geocode="5014" >
    <entity type="Tambon" name="สันทรายหลวง" english="San Sai Luang" geocode="501401" />
    <entity type="Tambon" name="สันทรายน้อย" english="San Sai Noi" geocode="501402" />
    <entity type="Tambon" name="สันพระเนตร" english="San Phranet" geocode="501403" />
    <entity type="Tambon" name="สันนาเม็ง" english="San Na Meng" geocode="501404" />
    <entity type="Tambon" name="สันป่าเปา" english="San Pa Pao" geocode="501405" />
    <entity type="Tambon" name="หนองแหย่ง" english="Nong Yaeng" geocode="501406" />
    <entity type="Tambon" name="หนองจ๊อม" english="Nong Chom" geocode="501407" />
    <entity type="Tambon" name="หนองหาร" english="Nong Han" geocode="501408" />
    <entity type="Tambon" name="แม่แฝก" english="Mae Faek" geocode="501409" />
    <entity type="Tambon" name="แม่แฝกใหม่" english="Mae Faek Mai" geocode="501410" />
    <entity type="Tambon" name="เมืองเล็น" english="Mueang Len" geocode="501411" />
    <entity type="Tambon" name="ป่าไผ่" english="Pa Phai" geocode="501412" />
  </entity>
  <entity type="Amphoe" name="หางดง" english="Hang Dong" geocode="5015" >
    <entity type="Tambon" name="หางดง" english="Hang Dong" geocode="501501" />
    <entity type="Tambon" name="หนองแก๋ว" english="Nong Kaeo" geocode="501502" />
    <entity type="Tambon" name="หารแก้ว" english="Han Kaeo" geocode="501503" />
    <entity type="Tambon" name="หนองตอง" english="Nong Tong" geocode="501504" />
    <entity type="Tambon" name="ขุนคง" english="Khun Khong" geocode="501505" />
    <entity type="Tambon" name="สบแม่ข่า" english="Sop Mae Kha" geocode="501506" />
    <entity type="Tambon" name="บ้านแหวน" english="Ban Waen" geocode="501507" />
    <entity type="Tambon" name="สันผักหวาน" english="San Phak Wan" geocode="501508" />
    <entity type="Tambon" name="หนองควาย" english="Nong Khwai" geocode="501509" />
    <entity type="Tambon" name="บ้านปง" english="Ban Pong" geocode="501510" />
    <entity type="Tambon" name="น้ำแพร่" english="Nam Phrae" geocode="501511" />
  </entity>
  <entity type="Amphoe" name="ฮอด" english="Hot" geocode="5016" >
    <entity type="Tambon" name="หางดง" english="Hang Dong" geocode="501601" />
    <entity type="Tambon" name="ฮอด" english="Hot" geocode="501602" />
    <entity type="Tambon" name="บ้านตาล" english="Ban Tan" geocode="501603" />
    <entity type="Tambon" name="บ่อหลวง" english="Bo Luang" geocode="501604" />
    <entity type="Tambon" name="บ่อสลี" english="Bo Sali" geocode="501605" />
    <entity type="Tambon" name="นาคอเรือ" english="Na Kho Ruea" geocode="501606" />
  </entity>
  <entity type="Amphoe" name="ดอยเต่า" english="Doi Tao" geocode="5017" >
    <entity type="Tambon" name="ดอยเต่า" english="Doi Tao" geocode="501701" />
    <entity type="Tambon" name="ท่าเดื่อ" english="Tha Duea" geocode="501702" />
    <entity type="Tambon" name="มืดกา" english="Muet Ka" geocode="501703" />
    <entity type="Tambon" name="บ้านแอ่น" english="Ban Aen" geocode="501704" />
    <entity type="Tambon" name="บงตัน" english="Bong Tan" geocode="501705" />
    <entity type="Tambon" name="โปงทุ่ง" english="Pong Thung" geocode="501706" />
  </entity>
  <entity type="Amphoe" name="อมก๋อย" english="Omkoi" geocode="5018" >
    <entity type="Tambon" name="อมก๋อย" english="Omkoi" geocode="501801" />
    <entity type="Tambon" name="ยางเปียง" english="Yang Piang" geocode="501802" />
    <entity type="Tambon" name="แม่ตื่น" english="Mae Tuen" geocode="501803" />
    <entity type="Tambon" name="ม่อนจอง" english="Mon Chong" geocode="501804" />
    <entity type="Tambon" name="สบโขง" english="Sop Khong" geocode="501805" />
    <entity type="Tambon" name="นาเกียน" english="Na Kian" geocode="501806" />
  </entity>
  <entity type="Amphoe" name="สารภี" english="Saraphi" geocode="5019" >
    <entity type="Tambon" name="ยางเนิ้ง" english="Yang Noeng" geocode="501901" />
    <entity type="Tambon" name="สารภี" english="Saraphi" geocode="501902" />
    <entity type="Tambon" name="ชมภู" english="Chom Phu" geocode="501903" />
    <entity type="Tambon" name="ไชยสถาน" english="Chai Sathan" geocode="501904" />
    <entity type="Tambon" name="ขัวมุง" english="Khua Mung" geocode="501905" />
    <entity type="Tambon" name="หนองแฝก" english="Nong Faek" geocode="501906" />
    <entity type="Tambon" name="หนองผึ้ง" english="Nong Phueng" geocode="501907" />
    <entity type="Tambon" name="ท่ากว้าง" english="Tha Kwang" geocode="501908" />
    <entity type="Tambon" name="ดอนแก้ว" english="Don Kaeo" geocode="501909" />
    <entity type="Tambon" name="ท่าวังตาล" english="Tha Wang Tan" geocode="501910" />
    <entity type="Tambon" name="สันทราย" english="San Sai" geocode="501911" />
    <entity type="Tambon" name="ป่าบง" english="Pa Bong" geocode="501912" />
  </entity>
  <entity type="Amphoe" name="เวียงแหง" english="Wiang Haeng" geocode="5020" >
    <entity type="Tambon" name="เมืองแหง" english="Mueang Ngae" geocode="502001" />
    <entity type="Tambon" name="เปียงหลวง" english="Piang Luang" geocode="502002" />
    <entity type="Tambon" name="แสนไห" english="Saen Hai" geocode="502003" />
  </entity>
  <entity type="Amphoe" name="ไชยปราการ" english="Chai Prakan" geocode="5021" >
    <entity type="Tambon" name="ปงตำ" english="Pong Tam" geocode="502101" />
    <entity type="Tambon" name="ศรีดงเย็น" english="Si Dong Yen" geocode="502102" />
    <entity type="Tambon" name="แม่ทะลบ" english="Mae Thalop" geocode="502103" />
    <entity type="Tambon" name="หนองบัว" english="Nong Bua" geocode="502104" />
  </entity>
  <entity type="Amphoe" name="แม่วาง" english="Mae Wang" geocode="5022" >
    <entity type="Tambon" name="บ้านกาด" english="Ban Kat" geocode="502201" />
    <entity type="Tambon" name="ทุ่งปี้" english="Thung Pi" geocode="502202" />
    <entity type="Tambon" name="ทุ่งรวงทอง" english="Thung Ruang Thong" geocode="502203" />
    <entity type="Tambon" name="แม่วิน" english="Mae Win" geocode="502204" />
    <entity type="Tambon" name="ดอนเปา" english="Don Pao" geocode="502205" />
  </entity>
  <entity type="Amphoe" name="แม่ออน" english="Mae On" geocode="5023" >
    <entity type="Tambon" name="ออนเหนือ" english="On Nuea" geocode="502301" />
    <entity type="Tambon" name="ออนกลาง" english="On Klang" geocode="502302" />
    <entity type="Tambon" name="บ้านสหกรณ์" english="Ban Sahakon" geocode="502303" />
    <entity type="Tambon" name="ห้วยแก้ว" english="Huai Kaeo" geocode="502304" />
    <entity type="Tambon" name="แม่ทา" english="Mae Tha" geocode="502305" />
    <entity type="Tambon" name="ทาเหนือ" english="Tha Nuea" geocode="502306" />
  </entity>
  <entity type="Amphoe" name="ดอยหล่อ" english="Doi Lo" geocode="5024" >
    <entity type="Tambon" name="ดอยหล่อ" english="Doi Lo" geocode="502401" />
    <entity type="Tambon" name="สองแคว" english="Song Khwae" geocode="502402" />
    <entity type="Tambon" name="ยางคราม" english="Yang Khram" geocode="502403" />
    <entity type="Tambon" name="สันติสุข" english="Santi Suk" geocode="502404" />
  </entity>

  <entity type="ThesabanNakhon" name="เชียงใหม่" english="Chiang Mai" geocode="5099" parent="5001" />
  <entity type="ThesabanTambon" name="ช้างเผือก" english="Chang Phueak" geocode="5098" parent="5001" />
  <entity type="ThesabanTambon" name="จอมทอง" english="Chom Thong" geocode="5097" parent="5002" />
  <entity type="ThesabanTambon" name="บ้านหลวง" newname="จอมทอง" english="Ban Luang" geocode="5097" parent="5002" />
  <entity type="ThesabanTambon" name="แม่แจ่ม" english="Mae Chaem" geocode="5096" parent="5003" />
  <entity type="ThesabanTambon" name="เชียงดาว" english="Chiang Dao" geocode="5095" parent="5004" />
  <entity type="ThesabanTambon" name="เมืองงาย" english="Mueang Ngai" geocode="5094" parent="5004" />
  <entity type="ThesabanTambon" name="ดอยสะเก็ด" english="Doi Saket" geocode="5093" parent="5005" />
  <entity type="ThesabanTambon" name="เชิงดอย" newname="เชิงดอย" english="Choeng Doi" geocode="5093" parent="5005" />
  <entity type="ThesabanTambon" name="เมืองแกนพัฒนา" english="Mueang Kaen Phatthana" geocode="5092" parent="5006" />
  <entity type="ThesabanTambon" name="สันมหาพน" english="San Maha Phon" geocode="5091" parent="5006" />
  <entity type="ThesabanTambon" name="แม่ริม" english="Mae Rim" geocode="5090" parent="5007" />
  <entity type="ThesabanTambon" name="สะเมิงใต้" english="Samoeng Tai" geocode="5089" parent="5008" />
  <entity type="ThesabanTambon" name="บ้านแม่ข่า" english="Ban Mae Kha" geocode="5088" parent="5009" />
  <entity type="ThesabanTambon" name="เวียงฝาง" english="Wiang Fang" geocode="5087" parent="5009" />
  <entity type="ThesabanTambon" name="แม่อาย" english="Mae Ai" geocode="5086" parent="5010" />
  <entity type="ThesabanTambon" name="เวียงพร้าว" english="Wiang Phrao" geocode="5085" parent="5011" />
  <entity type="ThesabanTambon" name="บ้านกลาง" english="Ban Klang" geocode="5084" parent="5012" />
  <entity type="ThesabanTambon" name="สันป่าตอง" english="San Pa Tong" geocode="5083" parent="5012" />
  <entity type="ThesabanTambon" name="ยุหว่า" newname="สันป่าตอง" english="Yu Wa" geocode="5083" parent="5012" />
  <entity type="ThesabanTambon" name="ต้นเปา" english="Ton Pao" geocode="5082" parent="5013" />
  <entity type="ThesabanTambon" name="สันกำแพง" english="San Kamphaeng" geocode="5081" parent="5013" />
  <entity type="ThesabanTambon" name="แม่โจ้" english="Mae Cho" geocode="5080" parent="5014" />
  <entity type="ThesabanTambon" name="สันทรายหลวง" english="San Sai Luang" geocode="5079" parent="5014" />
  <entity type="ThesabanTambon" name="หนองตองพัฒนา" english="Nong Thong Phattana" geocode="5078" parent="5015" />
  <entity type="ThesabanTambon" name="หางดง" english="Hang Dong" geocode="5077" parent="5016" />
  <entity type="ThesabanTambon" name="ท่าข้าม" english="Tha Kham" geocode="5076" parent="5016" />
  <entity type="ThesabanTambon" name="ท่าเดื่อ" english="Tha Duea" geocode="5075" parent="5017" />
  <entity type="ThesabanTambon" name="อมก๋อย" english="Omkoi" geocode="5074" parent="5018" />
  <entity type="ThesabanTambon" name="ยางเนิ้ง" english="Yang Noeng" geocode="5073" parent="5019" />
  <entity type="ThesabanTambon" name="ไชยปราการ" english="Chai Prakan" geocode="5072" parent="5021" />
  <entity type="ThesabanTambon" name="แม่วาง" english="Mae Wang" geocode="5071" parent="5022" />
  <entity type="ThesabanTambon" name="บ้านกาด" english="Ban Kat" newname="แม่วาง" geocode="5071" parent="5022" />
  <entity type="ThesabanTambon" name="หนองป่าครั่ง" english="Nong Pa Khrang" geocode="5070" parent="5001" />

  <entity type="SakhaKwaeng" name="กาลวิละ" geocode="5051" parent="5001" comment="Part of Thesaban Nakhon Chiang Mai"/>
  <entity type="SakhaKwaeng" name="ศรีวิชัย" geocode="5052" parent="5001" comment="Part of Thesaban Nakhon Chiang Mai"/>
  <entity type="SakhaKwaeng" name="เม็งราย" geocode="5053" parent="5001" comment="Part of Thesaban Nakhon Chiang Mai"/>
</entity>